chatqhelper/__init__.py
chatqhelper/debug.py
chatqhelper/exceptions.py
chatqhelper/gsheet.py
chatqhelper/mqtt.py
chatqhelper/notifiers.py
chatqhelper/perf_tracking.py
chatqhelper/raft.py
chatqhelper/scheduler.py
chatqhelper/slack.py
chatqhelper/utils.py
chatqhelper/common/__init__.py
chatqhelper/common/constants.py
chatqhelper/handlers/__init__.py
chatqhelper/handlers/basic.py
chatqhelper-1.4.0.dist-info/METADATA
chatqhelper-1.4.0.dist-info/WHEEL
chatqhelper-1.4.0.dist-info/top_level.txt
chatqhelper-1.4.0.dist-info/RECORD
