Metadata-Version: 2.1
Name: chatqhelper
Version: 1.4.0
Summary: chatqhelper
Home-page: https://github.com/ChatQSG/chatq-helping-hand
Author: ChatQ
Author-email: UNKNOWN
License: UNKNOWN
Platform: UNKNOWN
Requires-Dist: paho-mqtt (==1.3.1)
Requires-Dist: schedule (==0.5.0)
Requires-Dist: gspread (==3.0.1)
Requires-Dist: google-api-python-client (==1.7.4)
Requires-Dist: oauth2client (==4.1.3)
Requires-Dist: slackclient (==1.3.0)
Requires-Dist: python-dateutil (==2.7.5)
